{
  "name": "oANOdFtnk2mQ9SuSKx86Enc6S3nu/pin_photos/e350f2ae-1f1e-4ce7-9f86-87afa53e97f3.jpg",
  "bucket": "pinfollowerr.appspot.com",
  "contentType": "image/jpeg",
  "metageneration": 1,
  "generation": 1652211221777,
  "storageClass": "STANDARD",
  "contentDisposition": "inline",
  "cacheControl": "public, max-age=3600",
  "contentEncoding": "identity",
  "downloadTokens": [
    "b8bb2541-7bc8-4830-96d5-7c1ae7780fc9"
  ],
  "etag": "Aq41ryKYNRWRgbNvELjHXmgyZH8",
  "timeCreated": "2022-05-10T19:33:41.776Z",
  "updated": "2022-05-10T19:33:41.776Z",
  "size": 112902,
  "md5Hash": "p+cZt5FEvMhxfADQGRAZsQ==",
  "crc32c": "810790443"
}